devbuddy/__init__.py
devbuddy/animations.py
devbuddy/cli.py
devbuddy/formatter.py
devbuddy/scaffolder.py
devbuddy/plugins/__init__.py
z0roday_devbuddy-0.3.0.dist-info/licenses/LICENSE
z0roday_devbuddy-0.3.0.dist-info/METADATA
z0roday_devbuddy-0.3.0.dist-info/WHEEL
z0roday_devbuddy-0.3.0.dist-info/entry_points.txt
z0roday_devbuddy-0.3.0.dist-info/top_level.txt
z0roday_devbuddy-0.3.0.dist-info/RECORD
