Metadata-Version: 2.4
Name: z0roday-devbuddy
Version: 0.3.0
Summary: A powerful CLI tool to automate coding tasks by z0roday
Author-email: z0roday <contact@z0roday.dev>
License: MIT
Project-URL: Homepage, https://github.com/z0roday/devbuddy
Project-URL: Bug Tracker, https://github.com/z0roday/devbuddy/issues
Project-URL: Documentation, https://github.com/z0roday/devbuddy/blob/main/README.md
Keywords: development,cli,tools,automation,devops
Classifier: Development Status :: 4 - Beta
Classifier: Environment :: Console
Classifier: Intended Audience :: Developers
Classifier: License :: OSI Approved :: MIT License
Classifier: Programming Language :: Python :: 3
Classifier: Programming Language :: Python :: 3.7
Classifier: Programming Language :: Python :: 3.8
Classifier: Programming Language :: Python :: 3.9
Classifier: Programming Language :: Python :: 3.10
Classifier: Programming Language :: Python :: 3.11
Classifier: Topic :: Software Development
Classifier: Topic :: Utilities
Requires-Python: >=3.7
License-File: LICENSE
Requires-Dist: click>=8.0
Requires-Dist: black>=23.0
Requires-Dist: autopep8>=2.0
Requires-Dist: yapf>=0.40.0
Requires-Dist: isort>=5.12.0
Requires-Dist: pytest>=7.0.0
Requires-Dist: pylint>=2.17.0
Requires-Dist: sphinx>=7.0.0
Requires-Dist: requests>=2.25.0
Provides-Extra: dev
Requires-Dist: build; extra == "dev"
Requires-Dist: twine; extra == "dev"
Dynamic: license-file
